{
  "_readme": "This file is the single source of truth for site navigation. Add a class, subject or chapter here, then drop matching .md files into /content/<class-id>/<subject-id>/<chapter-id>/{summary,qna,mock-paper}.md — no code changes needed. Chapter titles below are a starting scaffold based on long-standing NCERT chapter names; CBSE periodically rationalises the syllabus, so please cross-check titles/order against the current official syllabus (cbseacademic.nic.in) before publishing. See README.md for the full workflow, including the optional generate-index.mjs helper.",
  "siteName": "CBSE Prep",
  "classes": [
    {
      "id": "class-8",
      "label": "Class 8",
      "tagline": "Foundation year — build the habits that carry into Class 9 and 10.",
      "subjects": [
        {
          "id": "mathematics",
          "label": "Mathematics",
          "icon": "mathematics",
          "chapters": [
          ]
        },
        {
          "id": "science",
          "label": "Science",
          "icon": "science",
          "chapters": [
            { "id": "chapter-01-exploring-the-investigative-world-of-science", "number": 1, "title": "Exploring the Investigative World of Science" },
            { "id": "chapter-02-the-invisible-living-world-beyond-our-naked-eye", "number": 2, "title": "The Invisible Living World: Beyond Our Naked Eye" },
            { "id": "chapter-03-health-the-ultimate-treasure", "number": 3, "title": "Health: The Ultimate Treasure" },
            { "id": "chapter-04-electricity-magnetic-and-heating-effects", "number": 4, "title": "Electricity: Magnetic and Heating Effects" },
            { "id": "chapter-05-exploring-forces", "number": 5, "title": "Exploring Forces" },
            { "id": "chapter-06-pressure-winds-storms-cyclones", "number": 6, "title": "Pressure, Winds, Storms, and Cyclones" },
            { "id": "chapter-07-particulate-nature-of-matter", "number": 7, "title": "Particulate Nature of Matter" },
            { "id": "chapter-08-nature-of-matter-elements-compounds-mixtures", "number": 8, "title": "Nature of Matter : Elements, Compounds, and Mixtures" },
            { "id": "chapter-09-the-amazing-world-of-solutes-solvents-solutions", "number": 9, "title": "The Amazing World of Solutes, Solvents, and Solutions" },
            { "id": "chapter-10-light-mirrors-lenses", "number": 10, "title": "Light: Mirrors and Lenses" },
            { "id": "chapter-11-keeping-time-with-the-skies", "number": 11, "title": "Keeping Time with the Skies" },
            { "id": "chapter-12-how-nature-works-in-harmony", "number": 12, "title": "How Nature Works in Harmony" }
          ]
        },
        {
          "id": "social-science",
          "label": "Social Science",
          "icon": "social-science",
          "chapters": [
            { "id": "chapter-01-natural-resources-and-their-use", "number": 1, "title": "Natural Resources and Their Use" },
            { "id": "chapter-02-reshaping-indias-political-map", "number": 2, "title": "Reshaping India's Political Map" },
            { "id": "chapter-03-the-rise-of-the-marathas", "number": 3, "title": "The Rise of the Marathas" },
            { "id": "chapter-04-the-colonial-era-in-india", "number": 4, "title": "The Colonial Era in India" },
            { "id": "chapter-05-universal-franchise-and-indias-electoral-system", "number": 5, "title": "Universal Franchise and India’s Electoral System" },
            { "id": "chapter-06-the-parliamentary-system", "number": 6, "title": "The Parliamentary System: Legislature and Executive" },
            { "id": "chapter-07-factors-of-production", "number": 6, "title": "Factors of Production" }
          ]
        },
        {
          "id": "english",
          "label": "English",
          "icon": "english",
          "chapters": [
          ]
        },
        {
          "id": "hindi",
          "label": "Hindi",
          "icon": "hindi",
          "chapters": [
            { "id": "chapter-01-laakh-ki-choodiyan", "number": 1, "title": "लाख की चूड़ियाँ" }
          ]
        }
      ]
    },
    {
      "id": "class-9",
      "label": "Class 9",
      "tagline": "Where board-exam habits start forming — get ahead before Class 10.",
      "subjects": [
        {
          "id": "mathematics",
          "label": "Mathematics",
          "icon": "mathematics",
          "chapters": [
          ]
        },
        {
          "id": "science",
          "label": "Science",
          "icon": "science",
          "chapters": [
          ]
        },
        {
          "id": "social-science",
          "label": "Social Science",
          "icon": "social-science",
          "chapters": [
          ]
        },
        {
          "id": "english",
          "label": "English",
          "icon": "english",
          "chapters": [
          ]
        },
        {
          "id": "hindi",
          "label": "Hindi",
          "icon": "hindi",
          "chapters": [
          ]
        }
      ]
    },
    {
      "id": "class-10",
      "label": "Class 10",
      "tagline": "Board exam year. This is where every mock paper starts paying off.",
      "subjects": [
        {
          "id": "mathematics",
          "label": "Mathematics",
          "icon": "mathematics",
          "chapters": [
          ]
        },
        {
          "id": "science",
          "label": "Science",
          "icon": "science",
          "chapters": [
          ]
        },
        {
          "id": "social-science",
          "label": "Social Science",
          "icon": "social-science",
          "chapters": [
          ]
        },
        {
          "id": "english",
          "label": "English",
          "icon": "english",
          "chapters": [
          ]
        },
        {
          "id": "hindi",
          "label": "Hindi",
          "icon": "hindi",
          "chapters": [
          ]
        }
      ]
    }
  ]
}
